pychara/__init__.py
pychara/exceptions.py
pychara/session.py
pychara-0.9.3.dist-info/LICENSE
pychara-0.9.3.dist-info/METADATA
pychara-0.9.3.dist-info/WHEEL
pychara-0.9.3.dist-info/top_level.txt
pychara-0.9.3.dist-info/RECORD
