Metadata-Version: 2.1
Name: pychara
Version: 0.9.3
Summary: scraping support tool
Home-page: https://github.com/mypaceshun/pychara
Author: KAWAI Shun
Author-email: shun@osstech.co.jp
Maintainer: KAWAI Shun
Maintainer-email: shun@osstech.co.jp
License: MIT
Platform: UNKNOWN
Requires-Dist: beautifulsoup4 (==4.7.1)
Requires-Dist: requests (==2.21.0)
